LivestockCV/__init__.py
LivestockCV/core/CalculateAngle.py
LivestockCV/core/ContourDPT.py
LivestockCV/core/ContourMax.py
LivestockCV/core/__init__.py
LivestockCV/core/_debug.py
LivestockCV/core/_version.py
LivestockCV/core/analyze_color.py
LivestockCV/core/apply_mask.py
LivestockCV/core/bbox_to_bytes.py
LivestockCV/core/box.py
LivestockCV/core/cannyedge_detect.py
LivestockCV/core/classes.py
LivestockCV/core/color_palette.py
LivestockCV/core/contouring.py
LivestockCV/core/contours.py
LivestockCV/core/crop.py
LivestockCV/core/deprecation_warning.py
LivestockCV/core/dilate.py
LivestockCV/core/dimensions.py
LivestockCV/core/erode.py
LivestockCV/core/fatal_error.py
LivestockCV/core/frame_count.py
LivestockCV/core/gaussian_blur.py
LivestockCV/core/hello.py
LivestockCV/core/invert.py
LivestockCV/core/js_to_image.py
LivestockCV/core/plot_image.py
LivestockCV/core/print_image.py
LivestockCV/core/rgb2gray.py
LivestockCV/core/rgb2gray_hsv.py
LivestockCV/core/rgb2gray_lab.py
LivestockCV/core/rotate.py
LivestockCV/core/show_image.py
LivestockCV/core/take_photo.py
LivestockCV/core/figures/__init__.py
LivestockCV/core/figures/auto_threshold_methods.py
LivestockCV/core/figures/clustered_contours.py
LivestockCV/core/figures/colorize_masks.py
LivestockCV/core/figures/colorspaces.py
LivestockCV/core/figures/histogram.py
LivestockCV/core/figures/overlay_two_imgs.py
LivestockCV/core/figures/pseudocolor.py
LivestockCV/core/roi/__init__.py
LivestockCV/core/roi/roi2mask.py
LivestockCV/core/roi/roi_methods.py
LivestockCV/core/threshold/__init__.py
LivestockCV/core/threshold/threshold_methods.py
LivestockCV/core/transform/__init__.py
LivestockCV/core/transform/color_correction.py
LivestockCV/core/transform/nonuniform_illumination.py
LivestockCV/core/transform/rescale.py
LivestockCV/core/transform/resize.py
LivestockCV/core/transform/warp.py
LivestockCV-0.0.0.99.dist-info/LICENSE
LivestockCV-0.0.0.99.dist-info/METADATA
LivestockCV-0.0.0.99.dist-info/WHEEL
LivestockCV-0.0.0.99.dist-info/top_level.txt
LivestockCV-0.0.0.99.dist-info/RECORD
