Metadata-Version: 2.1
Name: LivestockCV
Version: 0.0.0.99
Summary: Beta testing version of LivestockCV
Home-page: https://github.com/pypa/sampleproject
Author: Ryan Jeon
Author-email: ryanjeon@iastate.edu
License: UNKNOWN
Project-URL: Bug Tracker, https://github.com/pypa/sampleproject/issues
Platform: UNKNOWN
Classifier: Programming Language :: Python :: 3
Classifier: License :: OSI Approved :: MIT License
Classifier: Operating System :: OS Independent
Requires-Python: >=3.6
License-File: LICENSE
